google_news_trends_mcp/__init__.py
google_news_trends_mcp/__main__.py
google_news_trends_mcp/cli.py
google_news_trends_mcp/news.py
google_news_trends_mcp/server.py
google_news_trends_mcp-0.2.6.dist-info/licenses/LICENSE
google_news_trends_mcp-0.2.6.dist-info/METADATA
google_news_trends_mcp-0.2.6.dist-info/WHEEL
google_news_trends_mcp-0.2.6.dist-info/entry_points.txt
google_news_trends_mcp-0.2.6.dist-info/top_level.txt
google_news_trends_mcp-0.2.6.dist-info/RECORD
