Metadata-Version: 2.4
Name: google-news-trends-mcp
Version: 0.2.6
Summary: An MCP server to access RSS feeds of Google News and Google Trends
Author-email: Jesse Manek <jesse.manek@gmail.com>
License-Expression: MIT
Project-URL: Homepage, https://github.com/jmanek/google-news-trends-mcp
Project-URL: Repository, https://github.com/jmanek/google-news-trends-mcp
Project-URL: Issues, https://github.com/jmanek/google-news-trends-mcp/issues
Keywords: google,news,rss,trends,mcp,fastmcp,llm,nlp
Requires-Python: >=3.10.18
License-File: LICENSE
Requires-Dist: asyncio>=3.4.3
Requires-Dist: click>=8.2.1
Requires-Dist: cloudscraper>=1.2.71
Requires-Dist: fastmcp>=2.9.2
Requires-Dist: gnews>=0.4.1
Requires-Dist: googlenewsdecoder>=0.1.7
Requires-Dist: lxml[html-clean]>=6.0.0
Requires-Dist: newspaper4k>=0.9.3.1
Requires-Dist: nltk>=3.9.1
Requires-Dist: playwright>=1.53.0
Requires-Dist: pydantic>=2.11.7
Requires-Dist: trendspy>=0.1.6
Dynamic: license-file
